Metadata-Version: 2.1
Name: usefulpy
Version: 0.7
Summary: The most useful functions in everyday life
Home-page: https://github.com/bersena911/usefulpy
Download-URL: https://github.com/bersena911/usefulpy/archive/0.6.tar.gz
Author: Mate Bersenadze
Author-email: matebersenadze@gmail.com
License: MIT
Keywords: math,dummy,useful
Classifier: Development Status :: 4 - Beta
Classifier: Intended Audience :: Developers
Classifier: License :: OSI Approved :: MIT License
Classifier: Programming Language :: Python :: 3.7
License-File: LICENSE.txt
